{"name": "Società_calcistiche_indiane", "id": 1009846, "predecessors": [{"name": "Sport_di_squadra", "id": 39757}], "successors": [{"name": "Calciatori_del_Dempo_S.C.", "id": 4518730}, {"name": "Calciatori_del_F.C._Pune_City", "id": 5071298}, {"name": "Calciatori_dell'ATK", "id": 5105333}, {"name": "Calciatori_dell'Odisha_F.C.", "id": 5167286}, {"name": "Calciatori_del_Chennaiyin_F.C.", "id": 9939832}, {"name": "Calciatori_del_Kerala_Blasters_F.C.", "id": 9591987}, {"name": "Calciatori_del_Mumbai_City_F.C.", "id": 8747471}, {"name": "Calciatori_del_Jamshedpur_F.C.", "id": 9939629}, {"name": "Calciatori_del_Punjab_F.C.", "id": 9834528}, {"name": "Calciatori_del_Bengaluru_F.C.", "id": 9939621}, {"name": "Calciatori_del_Mumbai_F.C.", "id": 9939661}, {"name": "Calciatori_del_NorthEast_United_F.C.", "id": 9939667}, {"name": "Calciatori_dell'Hyderabad_F.C.", "id": 9939679}, {"name": "Calciatori_del_Mohun_Bagan_S.G.", "id": 9939828}]}