{"name": "Juventus_F.C.", "id": 2212640, "predecessors": [{"name": "Aziende_della_città_metropolitana_di_Torino", "id": 1270938}, {"name": "Aziende_fondate_nel_1897", "id": 3813329}, {"name": "Insigniti_con_il_Collare_d'oro_al_merito_sportivo", "id": 4523469}, {"name": "Insigniti_con_la_Stella_al_merito_sportivo", "id": 4827141}, {"name": "Insigniti_con_la_medaglia_al_valore_atletico", "id": 4827112}, {"name": "Società_calcistiche_italiane", "id": 31066}, {"name": "Società_sportive_campioni_nazionali_di_calcio", "id": 4335609}, {"name": "Categorie", "id": 41474}, {"name": "Calcio_in_Italia", "id": 679263}], "successors": [{"name": "Stagioni_della_Juventus_F.C.", "id": 2212647}, {"name": "Allenatori_della_Juventus_F.C.", "id": 2212656}, {"name": "Dirigenti_della_Juventus_F.C.", "id": 2213204}, {"name": "Presidenti_della_Juventus_F.C.", "id": 2213221}, {"name": "Calciatori_della_Juventus_F.C.", "id": 2213321}, {"name": "Immagini_della_Juventus_F.C.", "id": 4769664}, {"name": "Incontri_della_Juventus_F.C.", "id": 5963776}, {"name": "Calciatrici_della_Juventus_F.C.", "id": 6482640}, {"name": "Calciatori_della_Juventus_Next_Gen", "id": 7585345}]}