{"name": "Punk", "id": 285270, "predecessors": [{"name": "Movimenti_giovanili", "id": 86639}, {"name": "Subculture", "id": 447775}, {"name": "Categorie", "id": 41474}], "successors": [{"name": "Etichette_discografiche_punk", "id": 588224}, {"name": "Album_rapcore", "id": 565351}, {"name": "Gruppi_musicali_pop_punk", "id": 404750}, {"name": "Album_pop_punk", "id": 604942}, {"name": "Singoli_pop_punk", "id": 1248774}, {"name": "EP_pop_punk", "id": 1267750}, {"name": "Musicisti_pop_punk", "id": 2477234}, {"name": "Gruppi_musicali_ska_punk", "id": 384091}, {"name": "Album_ska_punk", "id": 1164557}, {"name": "Singoli_ska_punk", "id": 1252563}, {"name": "Gruppi_musicali_skate_punk", "id": 420669}, {"name": "Album_skate_punk", "id": 1168014}, {"name": "Singoli_skate_punk", "id": 1248775}, {"name": "EP_skate_punk", "id": 1267790}, {"name": "Album_horror_punk", "id": 1164737}, {"name": "Gruppi_musicali_proto-punk", "id": 1880155}, {"name": "Album_proto-punk", "id": 1880157}, {"name": "Gruppi_musicali_folk_punk", "id": 797473}, {"name": "Album_folk_punk", "id": 1188952}, {"name": "Gruppi_musicali_garage_punk", "id": 797504}, {"name": "Album_garage_punk", "id": 1532310}, {"name": "Singoli_garage_punk", "id": 1713071}, {"name": "Gruppi_musicali_screamo", "id": 475954}, {"name": "Album_screamo", "id": 1636205}, {"name": "Gruppi_musicali_art_punk", "id": 2338284}, {"name": "Album_art_punk", "id": 2375847}, {"name": "Gruppi_musicali_street_punk", "id": 2747074}, {"name": "Album_street_punk", "id": 2747086}, {"name": "Album_mod_revival", "id": 2440336}, {"name": "Album_punk_blues", "id": 2408652}, {"name": "Gruppi_musicali_hardcore_punk", "id": 367307}, {"name": "Album_hardcore_punk", "id": 1017348}, {"name": "EP_hardcore_punk", "id": 1267786}, {"name": "Singoli_hardcore_punk", "id": 1568439}, {"name": "Musicisti_hardcore_punk", "id": 2477212}, {"name": "Gruppi_musicali_post-hardcore", "id": 1638021}, {"name": "Album_post-hardcore", "id": 1638023}, {"name": "EP_post-hardcore", "id": 1638051}, {"name": "Singoli_post-hardcore", "id": 1993415}, {"name": "Musicisti_post-hardcore", "id": 2477237}, {"name": "Gruppi_musicali_melodic_hardcore_punk", "id": 1084487}, {"name": "Album_melodic_hardcore_punk", "id": 1164555}, {"name": "Singoli_melodic_hardcore_punk", "id": 1248792}, {"name": "EP_melodic_hardcore_punk", "id": 1267792}, {"name": "Gruppi_musicali_punk_revival", "id": 1795109}, {"name": "Album_punk_revival", "id": 1891466}, {"name": "Singoli_punk_revival", "id": 2004643}, {"name": "EP_punk_revival", "id": 2032722}, {"name": "Musicisti_punk_revival", "id": 2477247}, {"name": "Gruppi_musicali_anarcho_punk", "id": 797479}, {"name": "Album_anarcho_punk", "id": 1188713}, {"name": "Gruppi_musicali_crust_punk", "id": 762529}, {"name": "Album_crust_punk", "id": 1741300}, {"name": "Album_glam_punk", "id": 1317666}]}