{"name": "Violenza", "id": 355534, "predecessors": [{"name": "Comportamento_umano", "id": 5299732}, {"name": "Diritto_penale", "id": 61494}, {"name": "Etnoantropologia", "id": 1653976}, {"name": "Psicologia_sociale", "id": 493491}, {"name": "Relazioni_sociali", "id": 335014}, {"name": "Sociologia_politica", "id": 491899}], "successors": [{"name": "Tortura", "id": 355531}, {"name": "Autori_di_attentati", "id": 5165285}, {"name": "Morti_assassinati", "id": 28116}, {"name": "Morti_per_incidente_aereo", "id": 3697472}, {"name": "Morti_per_incidente_stradale", "id": 3698191}, {"name": "Morti_per_suicidio", "id": 3869705}, {"name": "Morti_per_incendio", "id": 4671456}, {"name": "Morti_per_arma_da_fuoco", "id": 4708109}, {"name": "Morti_per_incidente_a_cavallo", "id": 5312745}, {"name": "Morti_per_naufragio", "id": 7622299}, {"name": "Morti_per_incidente_ferroviario", "id": 7783895}, {"name": "Morti_per_incidente_sciistico", "id": 9271350}]}