{"name": "Unità_militari_per_tipo", "id": 3936314, "predecessors": [{"name": "Categorie", "id": 41474}], "successors": [{"name": "Servizi_segreti", "id": 65982}, {"name": "Formazioni_tattiche", "id": 902687}, {"name": "Forze_speciali", "id": 1249701}, {"name": "Guardie_d'onore", "id": 1272436}, {"name": "Forze_terrestri", "id": 3114937}, {"name": "Unità_militari_corazzate", "id": 3897498}, {"name": "Unità_militari_mercenarie", "id": 4003749}, {"name": "Unità_straniere", "id": 4705453}, {"name": "Guardie_reali", "id": 5443839}, {"name": "Arma_di_fanteria", "id": 3405136}, {"name": "Unità_militari_di_fanteria", "id": 3871835}, {"name": "Unità_paramilitari", "id": 4003750}, {"name": "Unità_militari_degli_Alpini", "id": 3994829}, {"name": "Armi_d'artiglieria", "id": 391005}, {"name": "Divisioni_corazzate", "id": 3968963}]}