{"name": "Cinema_italiano", "id": 430878, "predecessors": [{"name": "Cultura_dell'Europa", "id": 2362180}, {"name": "Comunicazione", "id": 37234}, {"name": "Categorie", "id": 41474}], "successors": [{"name": "Scenografi_italiani", "id": 84400}, {"name": "Cinema_muto_italiano", "id": 147253}, {"name": "Doppiatori_italiani", "id": 263975}, {"name": "Critici_cinematografici_italiani", "id": 558276}, {"name": "Produttori_cinematografici_italiani", "id": 558535}, {"name": "Direttori_della_fotografia_italiani", "id": 633025}, {"name": "Montatori_italiani", "id": 800232}, {"name": "Premi_cinematografici_italiani", "id": 5337085}, {"name": "Registi_cinematografici_italiani", "id": 5359849}, {"name": "Sceneggiatori_italiani_del_XXI_secolo", "id": 5767656}, {"name": "Sceneggiatori_italiani_del_XX_secolo", "id": 5967155}, {"name": "Spaghetti_western", "id": 491246}, {"name": "Film_d'interesse_culturale_nazionale", "id": 1255065}, {"name": "Film_di_Totò", "id": 1877974}, {"name": "Film_poliziotteschi", "id": 1912291}, {"name": "Film_commedia_all'italiana", "id": 2471276}, {"name": "Film_per_la_televisione_italiani", "id": 2772370}, {"name": "Film_muti_italiani", "id": 2823942}, {"name": "Film_d'animazione_italiani", "id": 4524858}, {"name": "Film_documentari_italiani", "id": 4951767}, {"name": "Film_in_lingua_siciliana", "id": 2558387}, {"name": "Film_girati_in_Sicilia", "id": 3494488}, {"name": "Film_ambientati_in_Sicilia", "id": 3818720}, {"name": "Cortometraggi_muti_italiani", "id": 4767584}, {"name": "Film_del_neorealismo", "id": 2947348}, {"name": "Film_diretti_da_Pupi_Avati", "id": 2022997}, {"name": "Film_diretti_da_Vittorio_De_Sica", "id": 2037246}, {"name": "Film_diretti_da_Roberto_Rossellini", "id": 2713966}, {"name": "Film_diretti_da_Marco_Bellocchio", "id": 2852349}, {"name": "Film_diretti_da_Ettore_Scola", "id": 2859793}, {"name": "Film_diretti_da_Mario_Monicelli", "id": 2861549}, {"name": "Film_diretti_da_Luciano_Salce", "id": 2910926}, {"name": "Film_diretti_da_Mauro_Bolognini", "id": 2910928}, {"name": "Film_diretti_da_Luigi_Comencini", "id": 3238551}, {"name": "Film_diretti_da_Dino_Risi", "id": 3265785}, {"name": "Film_diretti_da_Lina_Wertmüller", "id": 3266178}, {"name": "Film_diretti_da_Marco_Ferreri", "id": 3266206}, {"name": "Film_diretti_da_Carlo_Lizzani", "id": 3334774}, {"name": "Film_diretti_da_Alessandro_Blasetti", "id": 3461085}, {"name": "Film_diretti_da_Alberto_Lattuada", "id": 3469316}, {"name": "Film_diretti_da_Tinto_Brass", "id": 3813515}, {"name": "Film_diretti_da_Pasquale_Festa_Campanile", "id": 3815347}, {"name": "Film_diretti_da_Sergio_Corbucci", "id": 3816013}, {"name": "Film_diretti_da_Neri_Parenti", "id": 3817160}, {"name": "Film_diretti_da_Carlo_Vanzina", "id": 3821194}, {"name": "Film_diretti_da_Steno", "id": 3823128}, {"name": "Film_diretti_da_Camillo_Mastrocinque", "id": 3928737}, {"name": "Film_diretti_da_Mario_Mattoli", "id": 3954398}, {"name": "Film_diretti_da_Mario_Amendola", "id": 4160296}, {"name": "Film_diretti_da_Mario_Bava", "id": 4161566}, {"name": "Film_diretti_da_Lamberto_Bava", "id": 4161575}, {"name": "Film_diretti_da_Mario_Camerini", "id": 4162667}, {"name": "Film_diretti_da_Giorgio_Bianchi", "id": 4170051}, {"name": "Film_diretti_da_Mario_Bianchi", "id": 4170230}, {"name": "Film_diretti_da_Mario_Bonnard", "id": 4170320}, {"name": "Film_diretti_da_Carlo_Ludovico_Bragaglia", "id": 4170328}, {"name": "Film_diretti_da_Alfonso_Brescia", "id": 4170353}, {"name": "Film_diretti_da_Guido_Brignone", "id": 4170473}, {"name": "Film_diretti_da_Carlo_Campogalliani", "id": 4170483}, {"name": "Film_diretti_da_Luigi_Capuano", "id": 4170758}, {"name": "Film_diretti_da_Giuliano_Carnimeo", "id": 4170762}, {"name": "Film_diretti_da_Enzo_Girolami_Castellari", "id": 4171811}, {"name": "Film_diretti_da_Bruno_Corbucci", "id": 4171896}, {"name": "Film_diretti_da_Mario_Costa", "id": 4171917}, {"name": "Film_diretti_da_Damiano_Damiani", "id": 4174366}, {"name": "Film_diretti_da_Sergio_Martino", "id": 4261640}, {"name": "Film_diretti_da_Marino_Girolami", "id": 4264374}, {"name": "Film_diretti_da_Mario_Soldati", "id": 4345523}, {"name": "Film_diretti_da_Raffaello_Matarazzo", "id": 4623154}, {"name": "Film_diretti_da_Carmine_Gallone", "id": 4935108}, {"name": "Film_diretti_da_Luigi_Zampa", "id": 4940746}, {"name": "Film_diretti_da_Umberto_Lenzi", "id": 5078622}, {"name": "Film_diretti_da_Carlo_Verdone", "id": 5093475}, {"name": "Film_diretti_da_Giacomo_Gentilomo", "id": 5384367}, {"name": "Film_diretti_da_Roberto_Bianchi_Montero", "id": 5385109}, {"name": "Film_diretti_da_Giorgio_Simonelli", "id": 5386743}, {"name": "Film_diretti_da_Domenico_Paolella", "id": 5394807}, {"name": "Film_diretti_da_Sergio_Grieco", "id": 5395638}, {"name": "Film_diretti_da_Augusto_Genina", "id": 5396528}, {"name": "Film_diretti_da_Enrico_Guazzoni", "id": 5954288}, {"name": "Film_diretti_da_Mario_Caserini", "id": 6081849}, {"name": "Film_diretti_da_Antonio_Margheriti", "id": 6265010}, {"name": "Film_diretti_da_Gennaro_Righelli", "id": 6411729}, {"name": "Film_diretti_da_Giorgio_Ferroni", "id": 7572558}, {"name": "Film_diretti_da_Ninì_Grassia", "id": 7664297}, {"name": "Film_diretti_da_Amleto_Palermi", "id": 8150532}, {"name": "Film_diretti_da_Riccardo_Freda", "id": 8343868}, {"name": "Film_diretti_da_Ferdinando_Baldi", "id": 8422262}, {"name": "Film_diretti_da_Nunzio_Malasomma", "id": 8820342}, {"name": "Film_diretti_da_Lucio_Fulci", "id": 9128309}, {"name": "Film_diretti_da_Mariano_Laurenti", "id": 9255916}, {"name": "Film_ambientati_nel_Lazio", "id": 2657809}, {"name": "Film_girati_nel_Lazio", "id": 4405386}, {"name": "Film_ambientati_a_Roma", "id": 1595587}, {"name": "Film_girati_a_Roma", "id": 4405380}, {"name": "Film_ambientati_in_Abruzzo", "id": 3212864}, {"name": "Film_girati_in_Abruzzo", "id": 4825278}, {"name": "Film_ambientati_in_Basilicata", "id": 2918952}, {"name": "Film_girati_a_Matera", "id": 6180894}, {"name": "Film_ambientati_in_Calabria", "id": 3973535}, {"name": "Film_girati_in_Calabria", "id": 4226754}, {"name": "Film_ambientati_in_Campania", "id": 2657802}, {"name": "Film_girati_in_Campania", "id": 3479653}, {"name": "Film_ambientati_in_Emilia-Romagna", "id": 3541957}, {"name": "Film_girati_in_Emilia-Romagna", "id": 4473981}, {"name": "Film_ambientati_in_Lombardia", "id": 2657805}, {"name": "Film_girati_in_Lombardia", "id": 4424871}, {"name": "Film_ambientati_in_Puglia", "id": 2969188}, {"name": "Film_girati_in_Puglia", "id": 3315406}, {"name": "Film_ambientati_in_Toscana", "id": 2659682}, {"name": "Film_girati_in_Toscana", "id": 4424886}, {"name": "Film_ambientati_a_Firenze", "id": 3787930}, {"name": "Film_girati_a_Firenze", "id": 4795618}, {"name": "Film_ambientati_in_Piemonte", "id": 3131615}, {"name": "Film_girati_in_Piemonte", "id": 4424888}, {"name": "Film_ambientati_in_Liguria", "id": 3552243}, {"name": "Film_girati_in_Liguria", "id": 4858807}, {"name": "Film_girati_nelle_Marche", "id": 4825239}, {"name": "Film_italiani_del_1997", "id": 5440869}, {"name": "Film_italiani_del_1983", "id": 5441034}, {"name": "Film_italiani_del_1958", "id": 5441043}, {"name": "Film_italiani_del_2002", "id": 5441470}, {"name": "Film_italiani_del_1959", "id": 5441858}, {"name": "Film_italiani_del_1960", "id": 5441859}, {"name": "Film_italiani_del_1961", "id": 5441860}, {"name": "Film_italiani_del_1962", "id": 5441861}, {"name": "Film_italiani_del_1963", "id": 5441862}, {"name": "Film_italiani_del_1964", "id": 5441863}, {"name": "Film_italiani_del_1965", "id": 5441864}, {"name": "Film_italiani_del_1966", "id": 5441865}, {"name": "Film_italiani_del_1967", "id": 5441866}, {"name": "Film_italiani_del_1968", "id": 5441867}, {"name": "Film_italiani_del_1969", "id": 5441868}, {"name": "Film_italiani_del_1970", "id": 5441869}, {"name": "Film_italiani_del_1971", "id": 5441870}, {"name": "Film_italiani_del_1972", "id": 5441872}, {"name": "Film_italiani_del_1973", "id": 5441873}, {"name": "Film_italiani_del_1974", "id": 5441875}, {"name": "Film_italiani_del_1975", "id": 5441877}, {"name": "Film_italiani_del_1976", "id": 5441878}, {"name": "Film_italiani_del_1977", "id": 5441880}, {"name": "Film_italiani_del_1978", "id": 5441881}, {"name": "Film_italiani_del_1979", "id": 5441882}, {"name": "Film_italiani_del_1957", "id": 5441883}, {"name": "Film_italiani_del_1980", "id": 5441884}, {"name": "Film_italiani_del_1956", "id": 5442117}, {"name": "Film_italiani_del_1955", "id": 5442119}, {"name": "Film_italiani_del_1954", "id": 5442121}, {"name": "Film_italiani_del_1953", "id": 5442123}, {"name": "Film_italiani_del_1952", "id": 5442124}, {"name": "Film_italiani_del_1951", "id": 5442125}, {"name": "Film_italiani_del_1950", "id": 5442127}, {"name": "Film_italiani_del_1949", "id": 5442128}, {"name": "Film_italiani_del_1948", "id": 5442129}, {"name": "Film_italiani_del_1947", "id": 5442130}, {"name": "Film_italiani_del_1946", "id": 5442131}, {"name": "Film_italiani_del_1945", "id": 5442132}, {"name": "Film_italiani_del_1943", "id": 5442134}, {"name": "Film_italiani_del_1942", "id": 5442135}, {"name": "Film_italiani_del_1941", "id": 5442136}, {"name": "Film_italiani_del_1940", "id": 5442137}, {"name": "Film_italiani_del_1939", "id": 5442138}, {"name": "Film_italiani_del_1938", "id": 5442139}, {"name": "Film_italiani_del_1937", "id": 5442141}, {"name": "Film_italiani_del_1936", "id": 5442142}, {"name": "Film_italiani_del_1935", "id": 5442143}, {"name": "Film_italiani_del_1934", "id": 5442144}, {"name": "Film_italiani_del_1933", "id": 5442145}, {"name": "Film_italiani_del_1924", "id": 5442157}, {"name": "Film_italiani_del_1923", "id": 5442158}, {"name": "Film_italiani_del_1922", "id": 5442159}, {"name": "Film_italiani_del_1921", "id": 5442160}, {"name": "Film_italiani_del_1920", "id": 5442163}, {"name": "Film_italiani_del_1919", "id": 5442167}, {"name": "Film_italiani_del_1918", "id": 5442169}, {"name": "Film_italiani_del_1917", "id": 5442171}, {"name": "Film_italiani_del_1916", "id": 5442172}, {"name": "Film_italiani_del_1915", "id": 5442174}, {"name": "Film_italiani_del_1914", "id": 5442177}, {"name": "Film_italiani_del_1913", "id": 5442180}, {"name": "Film_italiani_del_1912", "id": 5442182}, {"name": "Film_italiani_del_1990", "id": 5442816}, {"name": "Film_italiani_del_1991", "id": 5442817}, {"name": "Film_italiani_del_1992", "id": 5442818}, {"name": "Film_italiani_del_1993", "id": 5442819}, {"name": "Film_italiani_del_1994", "id": 5442821}, {"name": "Film_italiani_del_1995", "id": 5442822}, {"name": "Film_italiani_del_1996", "id": 5442824}, {"name": "Film_italiani_del_1998", "id": 5442833}, {"name": "Film_italiani_del_1999", "id": 5442834}, {"name": "Film_italiani_del_2000", "id": 5442835}, {"name": "Film_italiani_del_2001", "id": 5442836}, {"name": "Film_italiani_del_2003", "id": 5442837}, {"name": "Film_italiani_del_2004", "id": 5442838}, {"name": "Film_italiani_del_2005", "id": 5442839}, {"name": "Film_italiani_del_2006", "id": 5442840}, {"name": "Film_italiani_del_2007", "id": 5442841}, {"name": "Film_italiani_del_2008", "id": 5442843}, {"name": "Film_italiani_del_2009", "id": 5442845}, {"name": "Film_italiani_del_2010", "id": 5442859}, {"name": "Film_italiani_del_2011", "id": 5442860}, {"name": "Film_italiani_del_2012", "id": 5442861}, {"name": "Film_italiani_del_2013", "id": 5442862}, {"name": "Film_italiani_del_2014", "id": 5442863}, {"name": "Film_italiani_del_2015", "id": 5442864}, {"name": "Film_italiani_del_1981", "id": 5442942}, {"name": "Film_italiani_del_1982", "id": 5442947}, {"name": "Film_italiani_del_1984", "id": 5442954}, {"name": "Film_italiani_del_1985", "id": 5442956}, {"name": "Film_italiani_del_1986", "id": 5442958}, {"name": "Film_italiani_del_1987", "id": 5442959}, {"name": "Film_italiani_del_1988", "id": 5442960}, {"name": "Film_italiani_del_1989", "id": 5442961}, {"name": "Film_italiani_del_2016", "id": 5678692}, {"name": "Film_italiani_del_2017", "id": 6012585}, {"name": "Film_italiani_del_2018", "id": 6486043}, {"name": "Film_italiani_del_2019", "id": 7730517}, {"name": "Film_italiani_del_2020", "id": 8234445}, {"name": "Film_italiani_del_2021", "id": 8599262}, {"name": "Film_italiani_del_2022", "id": 9260668}, {"name": "Film_italiani_del_2023", "id": 9586758}, {"name": "Film_italiani_del_2024", "id": 9923205}, {"name": "Cortometraggi_italiani_del_1910", "id": 5442983}, {"name": "Cortometraggi_italiani_del_1911", "id": 5442985}, {"name": "Cortometraggi_italiani_del_1912", "id": 5442986}, {"name": "Cortometraggi_italiani_del_1913", "id": 5442987}, {"name": "Cortometraggi_italiani_del_1909", "id": 5443081}, {"name": "Cortometraggi_italiani_del_1908", "id": 5443083}, {"name": "Film_girati_a_Bologna", "id": 4473990}, {"name": "Film_ambientati_a_Palermo", "id": 4012207}, {"name": "Film_girati_a_Palermo", "id": 4926136}, {"name": "Film_storici_italiani", "id": 5328326}, {"name": "Film_commedia_italiani", "id": 10243586}]}