{"name": "Gestione_dei_dati", "id": 5065561, "predecessors": [{"name": "Categorie", "id": 41474}, {"name": "Project_management", "id": 1376657}], "successors": [{"name": "File_system", "id": 35883}, {"name": "Strutture_dati", "id": 77923}, {"name": "Gestione_della_memoria", "id": 115844}, {"name": "Web_semantico", "id": 2267588}, {"name": "Analisi_dei_dati", "id": 4106934}, {"name": "Basi_di_dati", "id": 4751912}, {"name": "Metadati", "id": 5799797}, {"name": "Content_management_system_liberi", "id": 4134752}, {"name": "Database_management_system", "id": 4195877}]}