{"name": "Movimenti_pittorici", "id": 57312, "predecessors": [{"name": "Movimenti_artistici", "id": 73947}, {"name": "Pittura", "id": 24734}], "successors": [{"name": "Futurismo", "id": 75151}, {"name": "Neoclassicismo", "id": 475175}, {"name": "Preraffaelliti", "id": 503999}, {"name": "Macchiaioli", "id": 1535144}, {"name": "Realismo_magico", "id": 2555887}, {"name": "Bentvueghels", "id": 4068372}, {"name": "Surrealismo", "id": 5161287}, {"name": "Scuola_ferrarese", "id": 6666317}, {"name": "Pittura_napoletana_del_Seicento", "id": 8565641}, {"name": "Dipinti_di_Salvador_Dalí", "id": 2580048}, {"name": "Pittori_barocchi", "id": 2664302}]}