{"name": "Arcipelaghi", "id": 669775, "predecessors": [{"name": "Geomorfologia", "id": 785776}], "successors": [{"name": "Novaja_Zemlja", "id": 4741846}, {"name": "Arcipelago_artico_canadese", "id": 4933776}, {"name": "Fauna_endemica_delle_Canarie", "id": 6254737}, {"name": "Cicladi", "id": 335494}, {"name": "Corfù", "id": 341285}, {"name": "Eolie", "id": 2737207}, {"name": "Isole_della_Laguna_Veneta", "id": 609861}, {"name": "Arcipelago_Severnaja_Zemlja", "id": 1988141}, {"name": "Arcipelago_Terra_di_Francesco_Giuseppe", "id": 3769838}, {"name": "Arcipelago_dell'imperatrice_Eugenia", "id": 4834185}, {"name": "Cestisti_americo-verginiani", "id": 7611312}, {"name": "Tenerife", "id": 2037021}, {"name": "La_Palma", "id": 2037054}, {"name": "Nati_a_Saint_Croix", "id": 8409728}, {"name": "Nati_a_Saint_Thomas_(Isole_Vergini_Americane)", "id": 8409742}, {"name": "Cestisti_del_Tenerife_C.B.", "id": 4276282}, {"name": "Cestisti_del_C.B._Canarias", "id": 4275736}, {"name": "Dodecaneso", "id": 333859}, {"name": "Calciatori_americo-verginiani_del_XXI_secolo", "id": 9878024}]}