{"name": "Marina_militare", "id": 679073, "predecessors": [{"name": "Categorie", "id": 41474}, {"name": "Nautica", "id": 54399}], "successors": [{"name": "Marine_militari", "id": 796255}, {"name": "Gradi_di_marina", "id": 1588525}, {"name": "Sommergibili", "id": 1653649}, {"name": "Navi_scuola", "id": 3097639}, {"name": "Incrociatori_della_Regia_Marina", "id": 1653487}, {"name": "Incrociatori_della_Royal_Navy", "id": 1656113}, {"name": "Incrociatori_della_United_States_Navy", "id": 3089386}, {"name": "Incrociatori_della_Marina_imperiale_giapponese", "id": 5541670}, {"name": "Unità_della_Real_Marina_del_Regno_delle_Due_Sicilie", "id": 822362}, {"name": "Unità_della_Kriegsmarine", "id": 823303}, {"name": "Unità_della_k.u.k._Kriegsmarine", "id": 858329}, {"name": "Unità_della_marina_peruviana", "id": 1431605}, {"name": "Sommergibili_della_Kaiserliche_Marine", "id": 5554661}, {"name": "Cacciatorpediniere_della_Regia_Marina", "id": 1653548}, {"name": "Sommergibili_della_Regia_Marina", "id": 1653644}, {"name": "Navi_da_battaglia_della_Regia_Marina", "id": 1687879}, {"name": "Torpediniere_della_Regia_Marina", "id": 2545643}, {"name": "Corvette_della_Regia_Marina", "id": 3447920}, {"name": "Fregate_della_Regia_Marina", "id": 3469761}, {"name": "Navi_ospedale_della_Regia_Marina", "id": 3565574}, {"name": "Incrociatori_ausiliari_della_Regia_Marina", "id": 3737421}, {"name": "Fregate_della_Marina_Militare", "id": 5549243}, {"name": "Corvette_della_Marina_Militare", "id": 5549338}, {"name": "Navi_da_battaglia_della_Royal_Navy", "id": 1656114}, {"name": "Cacciatorpediniere_della_Royal_Navy", "id": 1656125}, {"name": "Portaerei_della_Royal_Navy", "id": 1656129}, {"name": "Vascelli_della_Royal_Navy", "id": 2342570}, {"name": "Sommergibili_della_Royal_Navy", "id": 5555710}, {"name": "Naviglio_militare_della_seconda_guerra_mondiale", "id": 721328}, {"name": "Naviglio_militare_della_prima_guerra_mondiale", "id": 886586}, {"name": "Film_di_sottomarini", "id": 2150282}, {"name": "Tipi_di_sottomarino", "id": 2837930}, {"name": "Classi_di_fregate", "id": 4735856}, {"name": "Navi_da_battaglia_della_United_States_Navy", "id": 3089388}, {"name": "Classi_di_unità_per_la_guerra_di_mine", "id": 4738912}, {"name": "Classi_di_unità_litoranee", "id": 627027}, {"name": "Classi_di_corvette", "id": 4736298}, {"name": "Classi_di_cacciatorpediniere", "id": 627025}, {"name": "Cacciatorpediniere_della_United_States_Navy", "id": 4765384}, {"name": "Cacciatorpediniere_della_Marina_imperiale_giapponese", "id": 5543458}, {"name": "Portaerei_della_United_States_Navy", "id": 3089449}, {"name": "Classi_di_navi_da_appoggio_russe", "id": 2195370}, {"name": "Vascelli_della_Marina_della_Repubblica_di_Venezia", "id": 7810503}]}