{"name": "Società_calcistiche_spagnole", "id": 83981, "predecessors": [{"name": "Sport_di_squadra", "id": 39757}, {"name": "Categorie", "id": 41474}], "successors": [{"name": "Calciatori_dell'Athletic_Club", "id": 2249086}, {"name": "Allenatori_dell'Athletic_Club", "id": 2252507}, {"name": "Stagioni_dell'Athletic_Club", "id": 2257292}, {"name": "Calciatori_del_Bilbao_Athletic", "id": 2474120}, {"name": "Calciatori_del_Real_Racing_Club_de_Santander", "id": 2260813}, {"name": "Allenatori_del_Real_Racing_Club_de_Santander", "id": 2294495}, {"name": "Calciatori_del_Real_Racing_Club_de_Santander_B", "id": 2474160}, {"name": "Calciatori_del_Getafe_C.F.", "id": 2272152}, {"name": "Calciatori_del_Getafe_C.F._B", "id": 3318626}, {"name": "Calciatori_dell'Albacete_Balompié", "id": 2438146}, {"name": "Allenatori_dell'Albacete_Balompié", "id": 2438384}, {"name": "Calciatori_del_Cádiz_C.F.", "id": 2438515}, {"name": "Allenatori_del_Cádiz_C.F.", "id": 2448830}, {"name": "Calciatori_del_Cádiz_C.F._B", "id": 2688908}, {"name": "Allenatori_del_R.C._Celta_de_Vigo", "id": 2254103}, {"name": "Calciatori_del_R.C._Celta_de_Vigo", "id": 2254106}, {"name": "Calciatori_del_R.C._Celta_de_Vigo_B", "id": 2474132}, {"name": "Calciatori_del_R.C.D._Mallorca", "id": 2286290}, {"name": "Allenatori_del_R.C.D._Mallorca", "id": 2290220}, {"name": "Calciatori_del_R.C.D._Mallorca_B", "id": 2474150}, {"name": "Calciatori_del_Málaga_C.F.", "id": 2250769}, {"name": "Allenatori_del_Málaga_C.F.", "id": 2294431}, {"name": "Calciatori_del_Málaga_C.F._B", "id": 2484875}, {"name": "Calciatori_del_C.A._Osasuna", "id": 2254122}, {"name": "Allenatori_del_C.A._Osasuna", "id": 2294512}, {"name": "Calciatori_del_C.A._Osasuna_B", "id": 2474159}, {"name": "Calciatori_del_Real_Zaragoza", "id": 2253590}, {"name": "Allenatori_del_Real_Zaragoza", "id": 2254139}, {"name": "Calciatori_del_Real_Zaragoza_B", "id": 2474176}, {"name": "Stagioni_del_Real_Zaragoza", "id": 3371702}, {"name": "Calciatori_della_Real_Sociedad_de_Fútbol", "id": 2254126}, {"name": "Allenatori_della_Real_Sociedad_de_Fútbol", "id": 2275486}, {"name": "Calciatori_della_Real_Sociedad_de_Fútbol_B", "id": 2474178}, {"name": "Calciatori_del_Sevilla_F.C.", "id": 2250637}, {"name": "Allenatori_del_Sevilla_F.C.", "id": 2252942}, {"name": "Allenatori_del_Valencia_C.F.", "id": 2250699}, {"name": "Calciatori_del_Valencia_C.F.", "id": 2252521}, {"name": "Stagioni_del_Valencia_C.F.", "id": 2455375}, {"name": "Calciatori_del_Valencia_C.F._Mestalla", "id": 2474155}, {"name": "Calciatori_del_Villarreal_C.F.", "id": 2250746}, {"name": "Calciatori_del_Villarreal_C.F._B", "id": 2474200}, {"name": "Calciatori_del_Deportivo_Alavés", "id": 2464890}, {"name": "Allenatori_del_Deportivo_Alavés", "id": 2464893}, {"name": "Calciatori_del_Deportivo_Alavés_B", "id": 2474063}, {"name": "Calciatori_dell'Elche_C.F.", "id": 2465350}, {"name": "Allenatori_dell'Elche_C.F.", "id": 2465354}, {"name": "Calciatori_del_Levante_U.D.", "id": 2465723}, {"name": "Allenatori_del_Levante_U.D.", "id": 2465725}, {"name": "Calciatori_del_Levante_U.D._B", "id": 3305175}, {"name": "Calciatori_del_Real_Oviedo", "id": 2465764}, {"name": "Allenatori_del_Real_Oviedo", "id": 2465766}, {"name": "Calciatori_del_Real_Valladolid_C.F.", "id": 2465772}, {"name": "Allenatori_del_Real_Valladolid_C.F.", "id": 2465773}, {"name": "Calciatori_del_Real_Valladolid_C.F._B", "id": 2474182}, {"name": "Calciatori_del_Real_Sporting_de_Gijón", "id": 2465777}, {"name": "Allenatori_del_Real_Sporting_de_Gijón", "id": 2465784}, {"name": "Calciatori_del_Real_Sporting_de_Gijón_B", "id": 3423693}, {"name": "Calciatori_del_Real_Club_Recreativo_de_Huelva", "id": 2465805}, {"name": "Allenatori_del_Real_Club_Recreativo_de_Huelva", "id": 2465817}, {"name": "Calciatori_del_Real_Unión_Club_de_Irún", "id": 2538658}, {"name": "Calciatori_dell'Arenas_Club_de_Getxo", "id": 2538654}, {"name": "Calciatori_della_S.D._Eibar", "id": 2538579}, {"name": "Calciatori_del_C.D._Baskonia", "id": 2538581}, {"name": "Calciatori_del_Barakaldo_C.F.", "id": 2538558}, {"name": "Calciatori_della_S.D._Indautxu", "id": 2558410}, {"name": "Calciatori_della_S.D._Amorebieta", "id": 2576292}, {"name": "Calciatori_del_F.C._Cartagena", "id": 2578286}, {"name": "Calciatori_della_S.D._Ponferradina", "id": 2599825}, {"name": "Calciatori_del_C.D._Castellón", "id": 2656201}, {"name": "Allenatori_del_C.D._Castellón", "id": 2656205}, {"name": "Calciatori_del_C.D._Numancia_de_Soria", "id": 2661433}, {"name": "Calciatori_del_Córdoba_C.F.", "id": 2661440}, {"name": "Allenatori_del_Córdoba_C.F.", "id": 2661442}, {"name": "Calciatori_del_C.E._Europa", "id": 2661866}, {"name": "Calciatori_del_C.E._l'Hospitalet", "id": 2661964}, {"name": "Calciatori_dell'U.D.A._Gramenet", "id": 2662858}, {"name": "Calciatori_della_S.D._Huesca", "id": 2663020}, {"name": "Allenatori_della_S.D._Huesca", "id": 2663021}, {"name": "Calciatori_del_C.F._Gavà", "id": 2666217}, {"name": "Calciatori_dell'A.D._Ceuta", "id": 2667964}, {"name": "Calciatori_del_Racing_Club_de_Ferrol", "id": 2667975}, {"name": "Calciatori_del_C.D._Lugo", "id": 2667990}, {"name": "Calciatori_del_C.D._Leganés", "id": 2668000}, {"name": "Calciatori_dell'U.D._Puertollano", "id": 2669387}, {"name": "Calciatori_del_C.D._Alcoyano", "id": 2669622}, {"name": "Calciatori_del_C.D._Guijuelo", "id": 2669653}, {"name": "Calciatori_del_C.D._Toledo", "id": 2670963}, {"name": "Calciatori_dell'A.D._Alcorcón", "id": 2670980}, {"name": "Calciatori_della_R.S.D._Alcalá", "id": 4633802}, {"name": "Calciatori_del_Burgos_C.F.", "id": 2671276}, {"name": "Calciatori_della_S.D._Compostela", "id": 2671338}, {"name": "Calciatori_dell'Écija_Balompié", "id": 2671357}, {"name": "Calciatori_del_Polideportivo_Ejido", "id": 2672955}, {"name": "Calciatori_della_R.S._Gimnástica_de_Torrelavega", "id": 2672972}, {"name": "Calciatori_del_Granada_C.F.", "id": 2673006}, {"name": "Allenatori_del_Granada_C.F.", "id": 2673019}, {"name": "Calciatori_del_Granada_C.F._B", "id": 6116154}, {"name": "Calciatori_del_C.D._Guadalajara_(Spagna)", "id": 2673057}, {"name": "Calciatori_del_C.D._Leonesa", "id": 2673094}, {"name": "Calciatori_del_C.D._Logroñés", "id": 2673395}, {"name": "Calciatori_della_Lorca_Deportiva_C.F.", "id": 3258622}, {"name": "Calciatori_del_Marbella_F.C.", "id": 2673417}, {"name": "Calciatori_dell'U.D._Melilla", "id": 2673426}, {"name": "Calciatori_del_C.D._Mirandés", "id": 3342685}, {"name": "Calciatori_dell'Ontinyent_C.F.", "id": 3128787}, {"name": "Calciatori_del_C.F._Palencia", "id": 2673479}, {"name": "Calciatori_del_Real_Jaén_C.F.", "id": 2673483}, {"name": "Calciatori_del_Terrassa_F.C.", "id": 2673519}, {"name": "Calciatori_dell'U.D._Vecindario", "id": 2673525}, {"name": "Calciatori_dello_Zamora_C.F.", "id": 2673530}, {"name": "Calciatori_dell'Orihuela_C.F.", "id": 2686886}, {"name": "Calciatori_del_C.P._Cacereño", "id": 2686920}, {"name": "Calciatori_del_F.C._Andorra", "id": 3426842}, {"name": "Calciatori_della_Real_Balompedica_Linense", "id": 3654102}, {"name": "Calciatori_del_C.D._Ourense", "id": 4237839}, {"name": "Stagioni_del_F.C._Barcelona", "id": 2265410}, {"name": "Stagioni_del_Club_Atlético_de_Madrid", "id": 2448467}, {"name": "Stagioni_del_Real_Madrid_C.F.", "id": 2455202}, {"name": "Calciatori_del_C.D._Atlético_Baleares", "id": 5633517}, {"name": "Calciatrici_del_Levante_U.D.", "id": 5640302}, {"name": "Calciatrici_dell'Athletic_Club", "id": 2729335}, {"name": "Calciatrici_del_Valencia_C.F._Femenino", "id": 6114417}, {"name": "Calciatrici_del_Sevilla_F.C.", "id": 6446774}, {"name": "Calciatori_del_Lorca_F.C.", "id": 6490435}, {"name": "Calciatori_del_Real_Betis_Balompié", "id": 2251005}, {"name": "Allenatori_del_Real_Betis_Balompié", "id": 2252940}, {"name": "Calciatori_del_Real_Betis_Balompié_B", "id": 2474118}, {"name": "Calciatori_del_Sevilla_Atlético_Club", "id": 2474192}, {"name": "Calciatori_del_C.E._Sabadell_F.C.", "id": 2662902}, {"name": "Allenatori_del_C.E._Sabadell_F.C.", "id": 2662903}, {"name": "Calciatori_del_C.D._Eldense", "id": 9909594}]}